README
setup.cfg
setup.py
Binner.egg-info/PKG-INFO
Binner.egg-info/SOURCES.txt
Binner.egg-info/dependency_links.txt
Binner.egg-info/top_level.txt
binner/__init__.py
binner/algo.py
binner/algo_code.py
binner/algo_multi.py
binner/algo_single.py
binner/algo_smallest.py
binner/binner_main.py
binner/collection.py
binner/collection_bin.py
binner/collection_item.py
binner/entity.py
binner/entity_artifact.py
binner/entity_bin.py
binner/entity_item.py
binner/entity_object.py
binner/entity_slot.py
binner/entity_space.py
binner/estimate.py
binner/exception.py
binner/helpers.py
binner/runtime.py
binner/runtime_cli.py
binner/runtime_web.py
binner/runtime_web_api.py